setup.py
atlasctf_21_prod_15/__init__.py
atlasctf_21_prod_15.egg-info/PKG-INFO
atlasctf_21_prod_15.egg-info/SOURCES.txt
atlasctf_21_prod_15.egg-info/dependency_links.txt
atlasctf_21_prod_15.egg-info/top_level.txt