Metadata-Version: 2.1
Name: atlasctf_21_prod_15
Version: 99.99.99
Summary: Internal team utils
